odoo/addons/repair_picking_after_done/README.rst
odoo/addons/repair_picking_after_done/__init__.py
odoo/addons/repair_picking_after_done/__manifest__.py
odoo/addons/repair_picking_after_done/hooks.py
odoo/addons/repair_picking_after_done/i18n/ca.po
odoo/addons/repair_picking_after_done/i18n/es.po
odoo/addons/repair_picking_after_done/i18n/it.po
odoo/addons/repair_picking_after_done/i18n/repair_picking_after_done.pot
odoo/addons/repair_picking_after_done/models/__init__.py
odoo/addons/repair_picking_after_done/models/repair.py
odoo/addons/repair_picking_after_done/models/res_config_settings.py
odoo/addons/repair_picking_after_done/readme/CONFIGURE.md
odoo/addons/repair_picking_after_done/readme/CONTRIBUTORS.md
odoo/addons/repair_picking_after_done/readme/DESCRIPTION.md
odoo/addons/repair_picking_after_done/readme/ROADMAP.md
odoo/addons/repair_picking_after_done/readme/USAGE.md
odoo/addons/repair_picking_after_done/security/ir.model.access.csv
odoo/addons/repair_picking_after_done/static/description/icon.png
odoo/addons/repair_picking_after_done/static/description/index.html
odoo/addons/repair_picking_after_done/tests/__init__.py
odoo/addons/repair_picking_after_done/tests/test_repair_transfers.py
odoo/addons/repair_picking_after_done/tests/test_stock_move_split.py
odoo/addons/repair_picking_after_done/views/repair.xml
odoo/addons/repair_picking_after_done/views/res_config_settings_views.xml
odoo/addons/repair_picking_after_done/wizards/__init__.py
odoo/addons/repair_picking_after_done/wizards/repair_move_transfer.py
odoo/addons/repair_picking_after_done/wizards/repair_move_transfer_views.xml
odoo_addon_repair_picking_after_done-17.0.1.1.0.2.dist-info/METADATA
odoo_addon_repair_picking_after_done-17.0.1.1.0.2.dist-info/WHEEL
odoo_addon_repair_picking_after_done-17.0.1.1.0.2.dist-info/top_level.txt
odoo_addon_repair_picking_after_done-17.0.1.1.0.2.dist-info/RECORD
