Metadata-Version: 2.1
Name: odoo-addon-repair_picking_after_done
Version: 17.0.1.1.0.2
Requires-Python: >=3.10
Requires-Dist: odoo-addon-base_repair_config>=17.0dev,<17.1dev
Requires-Dist: odoo-addon-repair_stock>=17.0dev,<17.1dev
Requires-Dist: odoo-addon-repair_type>=17.0dev,<17.1dev
Requires-Dist: odoo-addon-repair_type_product_destination>=17.0dev,<17.1dev
Requires-Dist: odoo>=17.0a,<17.1dev
Summary: Transfer repaired move to another location directly from repair order
Home-page: https://github.com/OCA/repair
License: AGPL-3
Author: ForgeFlow, Odoo Community Association (OCA)
Author-email: support@odoo-community.org
Classifier: Programming Language :: Python
Classifier: Framework :: Odoo
Classifier: Framework :: Odoo :: 17.0
Classifier: License :: OSI Approved :: GNU Affero General Public License v3
Classifier: Development Status :: 3 - Alpha
